hxltm/__init__.py
hxltm/bin/0.77.995.yml
hxltm/bin/__init__.py
hxltm/bin/cor.hxltm.215.yml
hxltm/bin/hxltmcli.py
hxltm/bin/hxltmdexml.py
hxltm_eticaai-0.9.1.dist-info/METADATA
hxltm_eticaai-0.9.1.dist-info/WHEEL
hxltm_eticaai-0.9.1.dist-info/entry_points.txt
hxltm_eticaai-0.9.1.dist-info/top_level.txt
hxltm_eticaai-0.9.1.dist-info/RECORD
