Metadata-Version: 2.1
Name: hxltm-eticaai
Version: 0.9.1
Summary: Multilingual Terminology in Humanitarian Language Exchange (HXLTM) - reference implementation.
Home-page: https://github.com/EticaAI/hxltm
Author: Emerson Rocha
Author-email: rocha@ieee.org
Project-URL: Bug Tracker, https://github.com/EticaAI/hxltm/issues
Classifier: Programming Language :: Python :: 3
Classifier: License :: OSI Approved :: The Unlicense (Unlicense)
Classifier: Operating System :: OS Independent
Classifier: Typing :: Typed
Classifier: Topic :: Utilities
Requires-Python: >=3.7
